nersights/__init__.py
nersights/constants.py
nersights/dataset.py
nersights/insights.py
nersights/loaders.py
nersights/recognizer.py
nersights/stats.py
nersights/types.py
nersights/validation.py
nersights-0.0.1.dist-info/LICENSE
nersights-0.0.1.dist-info/WHEEL
nersights-0.0.1.dist-info/METADATA
nersights-0.0.1.dist-info/RECORD
