Metadata-Version: 2.1
Name: nersights
Version: 0.0.1
Summary: Typer, build great CLIs. Easy to code. Based on Python type hints.
Home-page: https://github.com/kabirkhan/nersights
License: UNKNOWN
Author: Kabir Khan
Author-email: kabirkhan1137@outlook.com
Requires-Python: >=3.6
Classifier: Intended Audience :: Information Technology
Classifier: Intended Audience :: System Administrators
Classifier: Operating System :: OS Independent
Classifier: Programming Language :: Python :: 3
Classifier: Programming Language :: Python
Classifier: Topic :: Software Development :: Libraries :: Application Frameworks
Classifier: Topic :: Software Development :: Libraries :: Python Modules
Classifier: Topic :: Software Development :: Libraries
Classifier: Topic :: Software Development
Classifier: Typing :: Typed
Classifier: Development Status :: 4 - Beta
Classifier: Intended Audience :: Developers
Classifier: Programming Language :: Python :: 3 :: Only
Classifier: Programming Language :: Python :: 3.6
Classifier: Programming Language :: Python :: 3.7
Classifier: Programming Language :: Python :: 3.8
Classifier: License :: OSI Approved :: MIT License
Requires-Dist: spacy >= 2.2.1, <3.0.0
Requires-Dist: pydantic == 1.3
Requires-Dist: colorama ; extra == "all"
Requires-Dist: click-completion ; extra == "all"
Requires-Dist: jupyterlab >= 1.2.0, <1.3 ; extra == "dev"
Requires-Dist: mkdocs ; extra == "doc"
Requires-Dist: mkdocs-material ; extra == "doc"
Requires-Dist: markdown-include ; extra == "doc"
Requires-Dist: mkautodoc ; extra == "doc"
Requires-Dist: pytest >=4.4.0 ; extra == "test"
Requires-Dist: pytest-cov ; extra == "test"
Requires-Dist: coverage ; extra == "test"
Requires-Dist: pytest-xdist ; extra == "test"
Requires-Dist: pytest-sugar ; extra == "test"
Requires-Dist: mypy ; extra == "test"
Requires-Dist: black ; extra == "test"
Requires-Dist: isort ; extra == "test"
Project-URL: Documentation, https://kabirkhan.github.io/nersights
Provides-Extra: all
Provides-Extra: dev
Provides-Extra: doc
Provides-Extra: test
